nlpbirdge_proto/__init__.py
nlpbirdge_proto/_file_info.py
nlpbirdge_proto/_package_info.py
nlpbirdge_proto/datetime_helpers.py
nlpbirdge_proto/enums.py
nlpbirdge_proto/fields.py
nlpbirdge_proto/message.py
nlpbirdge_proto/modules.py
nlpbirdge_proto/primitives.py
nlpbirdge_proto/utils.py
nlpbirdge_proto/version.py
nlpbirdge_proto/marshal/__init__.py
nlpbirdge_proto/marshal/compat.py
nlpbirdge_proto/marshal/marshal.py
nlpbirdge_proto/marshal/collections/__init__.py
nlpbirdge_proto/marshal/collections/maps.py
nlpbirdge_proto/marshal/collections/repeated.py
nlpbirdge_proto/marshal/rules/__init__.py
nlpbirdge_proto/marshal/rules/bytes.py
nlpbirdge_proto/marshal/rules/dates.py
nlpbirdge_proto/marshal/rules/enums.py
nlpbirdge_proto/marshal/rules/field_mask.py
nlpbirdge_proto/marshal/rules/message.py
nlpbirdge_proto/marshal/rules/stringy_numbers.py
nlpbirdge_proto/marshal/rules/struct.py
nlpbirdge_proto/marshal/rules/wrappers.py
nlpbridge_proto/__init__.py
nlpbridge_proto/_file_info.py
nlpbridge_proto/_package_info.py
nlpbridge_proto/datetime_helpers.py
nlpbridge_proto/enums.py
nlpbridge_proto/fields.py
nlpbridge_proto/message.py
nlpbridge_proto/modules.py
nlpbridge_proto/primitives.py
nlpbridge_proto/utils.py
nlpbridge_proto/version.py
nlpbridge_proto/marshal/__init__.py
nlpbridge_proto/marshal/compat.py
nlpbridge_proto/marshal/marshal.py
nlpbridge_proto/marshal/collections/__init__.py
nlpbridge_proto/marshal/collections/maps.py
nlpbridge_proto/marshal/collections/repeated.py
nlpbridge_proto/marshal/rules/__init__.py
nlpbridge_proto/marshal/rules/bytes.py
nlpbridge_proto/marshal/rules/dates.py
nlpbridge_proto/marshal/rules/enums.py
nlpbridge_proto/marshal/rules/field_mask.py
nlpbridge_proto/marshal/rules/message.py
nlpbridge_proto/marshal/rules/stringy_numbers.py
nlpbridge_proto/marshal/rules/struct.py
nlpbridge_proto/marshal/rules/wrappers.py
proto/__init__.py
proto/_file_info.py
proto/_package_info.py
proto/datetime_helpers.py
proto/enums.py
proto/fields.py
nlpbridge_proto-0.1.2.dist-info/LICENSE
nlpbridge_proto-0.1.2.dist-info/METADATA
nlpbridge_proto-0.1.2.dist-info/WHEEL
nlpbridge_proto-0.1.2.dist-info/entry_points.txt
nlpbridge_proto-0.1.2.dist-info/top_level.txt
nlpbridge_proto-0.1.2.dist-info/RECORD
