Metadata-Version: 2.1
Name: nlpbridge-proto
Version: 0.1.2
Summary: proto packge
Home-page: https://github.com/Vitalis001/proto/tree/main
Author: 
Author-email: 
License: MIT
Classifier: Programming Language :: Python :: 3
Classifier: License :: OSI Approved :: MIT License
Classifier: Operating System :: OS Independent
Requires-Python: >=3.10
License-File: LICENSE
